{
  "brands": [
    {
      "name": "DIOR",
      "slug": "dior",
      "description": null,
      "logo_url": null,
      "website_url": null,
      "is_active": true,
      "sort_order": 11
    },
    {
      "name": "L'HOMME",
      "slug": "l-homme",
      "description": null,
      "logo_url": null,
      "website_url": null,
      "is_active": true,
      "sort_order": 2
    },
    {
      "name": "SAUVAGE",
      "slug": "sauvage",
      "description": null,
      "logo_url": null,
      "website_url": null,
      "is_active": true,
      "sort_order": 3
    },
    {
      "name": "NISHANE",
      "slug": "nishane",
      "description": null,
      "logo_url": null,
      "website_url": null,
      "is_active": true,
      "sort_order": 10
    },
    {
      "name": "JPG",
      "slug": "jpg",
      "description": null,
      "logo_url": null,
      "website_url": null,
      "is_active": true,
      "sort_order": 21
    },
    {
      "name": "YSL",
      "slug": "ysl",
      "description": null,
      "logo_url": null,
      "website_url": null,
      "is_active": true,
      "sort_order": 21
    },
    {
      "name": "XERJOFF",
      "slug": "xerjoff",
      "description": null,
      "logo_url": null,
      "website_url": null,
      "is_active": true,
      "sort_order": 9
    },
    {
      "name": "AMOUAGE",
      "slug": "amouage",
      "description": null,
      "logo_url": null,
      "website_url": null,
      "is_active": true,
      "sort_order": 8
    },
    {
      "name": "MORESQUE",
      "slug": "moresque",
      "description": null,
      "logo_url": null,
      "website_url": null,
      "is_active": true,
      "sort_order": 9
    },
    {
      "name": "PARFUMS",
      "slug": "parfums",
      "description": null,
      "logo_url": null,
      "website_url": null,
      "is_active": true,
      "sort_order": 18
    },
    {
      "name": "BLEND",
      "slug": "blend",
      "description": null,
      "logo_url": null,
      "website_url": null,
      "is_active": true,
      "sort_order": 11
    },
    {
      "name": "TOM FORD",
      "slug": "tom-ford",
      "description": null,
      "logo_url": null,
      "website_url": null,
      "is_active": true,
      "sort_order": 15
    },
    {
      "name": "ARMANI",
      "slug": "armani",
      "description": null,
      "logo_url": null,
      "website_url": null,
      "is_active": true,
      "sort_order": 16
    },
    {
      "name": "NANSHE",
      "slug": "nanshe",
      "description": null,
      "logo_url": null,
      "website_url": null,
      "is_active": true,
      "sort_order": 14
    },
    {
      "name": "GUCCI",
      "slug": "gucci",
      "description": null,
      "logo_url": null,
      "website_url": null,
      "is_active": true,
      "sort_order": 15
    },
    {
      "name": "LOUIS",
      "slug": "louis",
      "description": null,
      "logo_url": null,
      "website_url": null,
      "is_active": true,
      "sort_order": 16
    },
    {
      "name": "MFK",
      "slug": "mfk",
      "description": null,
      "logo_url": null,
      "website_url": null,
      "is_active": true,
      "sort_order": 17
    },
    {
      "name": "PARFUM",
      "slug": "parfum",
      "description": null,
      "logo_url": null,
      "website_url": null,
      "is_active": true,
      "sort_order": 18
    },
    {
      "name": "ROJA",
      "slug": "roja",
      "description": null,
      "logo_url": null,
      "website_url": null,
      "is_active": true,
      "sort_order": 19
    },
    {
      "name": "PRADA",
      "slug": "prada",
      "description": null,
      "logo_url": null,
      "website_url": null,
      "is_active": true,
      "sort_order": 20
    }
  ],
  "categories": [
    {
      "id": "5",
      "name": "PARFUMS HOMME",
      "slug": "parfums-homme",
      "url": "https://pafen-dz.com/category/5/parfums-homme",
      "description": null,
      "image_url": null,
      "parent_id": null,
      "is_active": true,
      "sort_order": 15
    },
    {
      "id": "6",
      "name": "PARFUMS FEMME",
      "slug": "parfums-femme",
      "url": "https://pafen-dz.com/category/6/parfums-femme",
      "description": null,
      "image_url": null,
      "parent_id": null,
      "is_active": true,
      "sort_order": 15
    },
    {
      "id": "7",
      "name": "COFFRET FEMME",
      "slug": "coffret-femme",
      "url": "https://pafen-dz.com/category/7/coffret-femme",
      "description": null,
      "image_url": null,
      "parent_id": null,
      "is_active": true,
      "sort_order": 15
    },
    {
      "id": "8",
      "name": "COFFRET HOMME",
      "slug": "coffret-homme",
      "url": "https://pafen-dz.com/category/8/coffret-homme",
      "description": null,
      "image_url": null,
      "parent_id": null,
      "is_active": true,
      "sort_order": 15
    },
    {
      "id": "10",
      "name": "PARFUMS DE NICHE",
      "slug": "parfums-de-niche",
      "url": "https://pafen-dz.com/category/10/parfums-de-niche",
      "description": null,
      "image_url": null,
      "parent_id": null,
      "is_active": true,
      "sort_order": 15
    },
    {
      "id": "11",
      "name": "DEODORANT HOMME",
      "slug": "deodorant-homme",
      "url": "https://pafen-dz.com/category/11/deodorant-homme",
      "description": null,
      "image_url": null,
      "parent_id": null,
      "is_active": true,
      "sort_order": 15
    },
    {
      "id": "12",
      "name": "DEODORANT FEMME",
      "slug": "deodorant-femme",
      "url": "https://pafen-dz.com/category/12/deodorant-femme",
      "description": null,
      "image_url": null,
      "parent_id": null,
      "is_active": true,
      "sort_order": 15
    },
    {
      "id": "13",
      "name": "GEL DOUCHE POUR HOMME",
      "slug": "gel-douche-pour-homme",
      "url": "https://pafen-dz.com/category/13/gel-douche-pour-homme",
      "description": null,
      "image_url": null,
      "parent_id": null,
      "is_active": true,
      "sort_order": 15
    },
    {
      "id": "14",
      "name": "LAIT DE CORPS",
      "slug": "lait-de-corps",
      "url": "https://pafen-dz.com/category/14/lait-de-corps",
      "description": null,
      "image_url": null,
      "parent_id": null,
      "is_active": true,
      "sort_order": 15
    },
    {
      "id": "15",
      "name": "PARFUM BÉBÉ/ ENFANT /FILLE / Garçon",
      "slug": "parfum-bebe-enfant-fille-garcon",
      "url": "https://pafen-dz.com/category/15/parfum-bébé-enfant-fille-garçon",
      "description": null,
      "image_url": null,
      "parent_id": null,
      "is_active": true,
      "sort_order": 15
    },
    {
      "id": "16",
      "name": "CREME POUR LES MAINS",
      "slug": "creme-pour-les-mains",
      "url": "https://pafen-dz.com/category/16/creme-pour-les-mains",
      "description": null,
      "image_url": null,
      "parent_id": null,
      "is_active": true,
      "sort_order": 15
    },
    {
      "id": "19",
      "name": "GEL DOUCHE POUR FEMME",
      "slug": "gel-douche-pour-femme",
      "url": "https://pafen-dz.com/category/19/gel-douche-pour-femme",
      "description": null,
      "image_url": null,
      "parent_id": null,
      "is_active": true,
      "sort_order": 15
    },
    {
      "id": "20",
      "name": "Maquillage",
      "slug": "maquillage",
      "url": "https://pafen-dz.com/category/20/maquillage",
      "description": null,
      "image_url": null,
      "parent_id": null,
      "is_active": true,
      "sort_order": 15
    },
    {
      "id": "21",
      "name": "BRUME",
      "slug": "brume",
      "url": "https://pafen-dz.com/category/21/brume",
      "description": null,
      "image_url": null,
      "parent_id": null,
      "is_active": true,
      "sort_order": 15
    }
  ],
  "products": [
    {
      "name": "DIOR HOMME EDT 100 ML *",
      "slug": "dior-homme-edt-100-ml",
      "description": null,
      "price": 19500,
      "price_text": "19500 DZD",
      "currency": "DZD",
      "image_url": null,
      "brand": "DIOR",
      "sku": "1168",
      "is_active": true,
      "stock_quantity": 0,
      "url": "https://pafen-dz.com/product/1168-dior-homme-100ml-edt-le-nouveau"
    },
    {
      "name": "L'HOMME IDEAL EXTREME EDP 100ML",
      "slug": "l-homme-ideal-extreme-edp-100ml",
      "description": null,
      "price": 19500,
      "price_text": "19500 DZD",
      "currency": "DZD",
      "image_url": null,
      "brand": "L'HOMME",
      "sku": "1321",
      "is_active": true,
      "stock_quantity": 0,
      "url": "https://pafen-dz.com/product/1321-lhomme-ideal-extreme-100ml-edp"
    },
    {
      "name": "SAUVAGE LE PARFUM 60ML",
      "slug": "sauvage-le-parfum-60ml",
      "description": null,
      "price": 24000,
      "price_text": "24000 DZD",
      "currency": "DZD",
      "image_url": null,
      "brand": "SAUVAGE",
      "sku": "1551",
      "is_active": true,
      "stock_quantity": 0,
      "url": "https://pafen-dz.com/product/1551-sauvage-60ml-parfum"
    },
    {
      "name": "NISHANE HUNDRED SILENT WAYS EXTRAIT DE PARFUM 100 ML",
      "slug": "nishane-hundred-silent-ways-extrait-de-parfum-100-ml",
      "description": null,
      "price": 48000,
      "price_text": "48000 DZD",
      "currency": "DZD",
      "image_url": null,
      "brand": "NISHANE",
      "sku": "1787",
      "is_active": true,
      "stock_quantity": 0,
      "url": "https://pafen-dz.com/product/1787-hundred-silent-ways-extrait-de-parfum-100-ml"
    },
    {
      "name": "LA NUIT DE L'HOMME LE PARFUM 100ML",
      "slug": "la-nuit-de-l-homme-le-parfum-100ml",
      "description": null,
      "price": 26000,
      "price_text": "26000 DZD",
      "currency": "DZD",
      "image_url": null,
      "brand": null,
      "sku": "97",
      "is_active": true,
      "stock_quantity": 0,
      "url": "https://pafen-dz.com/product/97-ysl-la-nuit-de-lhomme-100ml-le-parfum"
    },
    {
      "name": "DIOR MISS DIOR EDP 100 ML",
      "slug": "dior-miss-dior-edp-100-ml",
      "description": null,
      "price": 30000,
      "price_text": "30000 DZD",
      "currency": "DZD",
      "image_url": null,
      "brand": "DIOR",
      "sku": "184",
      "is_active": true,
      "stock_quantity": 0,
      "url": "https://pafen-dz.com/product/184-miss-dior-eau-de-parfum-100-ml"
    },
    {
      "name": "JPG ULTRA MALE EDT INTENSE 125 ML",
      "slug": "jpg-ultra-male-edt-intense-125-ml",
      "description": null,
      "price": 23000,
      "price_text": "23000 DZD",
      "currency": "DZD",
      "image_url": null,
      "brand": "JPG",
      "sku": "635",
      "is_active": true,
      "stock_quantity": 0,
      "url": "https://pafen-dz.com/product/635-8435415012027"
    },
    {
      "name": "YSL LA NUIT DE L'HOMME ROUGE EDP 100 ML",
      "slug": "ysl-la-nuit-de-l-homme-rouge-edp-100-ml",
      "description": null,
      "price": 24500,
      "price_text": "24500 DZD",
      "currency": "DZD",
      "image_url": null,
      "brand": "YSL",
      "sku": "909",
      "is_active": true,
      "stock_quantity": 0,
      "url": "https://pafen-dz.com/product/909-ysl-la-nuit-de-lhomme-100-ml-edp-new-edition-rouge"
    },
    {
      "name": "YSL LIBRE EDP 90 ML",
      "slug": "ysl-libre-edp-90-ml",
      "description": null,
      "price": 28000,
      "price_text": "28000 DZD",
      "currency": "DZD",
      "image_url": null,
      "brand": "YSL",
      "sku": "964",
      "is_active": true,
      "stock_quantity": 0,
      "url": "https://pafen-dz.com/product/964-ysl-libre-90ml-edp"
    },
    {
      "name": "YSL LIBRE EDP INTENSE 90 ML",
      "slug": "ysl-libre-edp-intense-90-ml",
      "description": null,
      "price": 29000,
      "price_text": "29000 DZD",
      "currency": "DZD",
      "image_url": null,
      "brand": "YSL",
      "sku": "1087",
      "is_active": true,
      "stock_quantity": 0,
      "url": "https://pafen-dz.com/product/1087-ysl-libre-edp-intense-90ml-femme"
    },
    {
      "name": "NISHANE MANA EXTRAIT DE PARFUM 50 ML",
      "slug": "nishane-mana-extrait-de-parfum-50-ml",
      "description": null,
      "price": 80500,
      "price_text": "80500 DZD",
      "currency": "DZD",
      "image_url": null,
      "brand": "NISHANE",
      "sku": "2609",
      "is_active": true,
      "stock_quantity": 0,
      "url": "https://pafen-dz.com/product/2609-nishane-mana-extrait-de-parfum-50ml"
    },
    {
      "name": "NISHANE NEFS EXTRAIT DE PARFUM 50ML",
      "slug": "nishane-nefs-extrait-de-parfum-50ml",
      "description": null,
      "price": 78500,
      "price_text": "78500 DZD",
      "currency": "DZD",
      "image_url": null,
      "brand": "NISHANE",
      "sku": "2610",
      "is_active": true,
      "stock_quantity": 0,
      "url": "https://pafen-dz.com/product/2610-nishane-nefs-extrait-de-parfum-50ml"
    },
    {
      "name": "NISHANE HACIVAT X EXTRAIT DE PARFUM 100 ML",
      "slug": "nishane-hacivat-x-extrait-de-parfum-100-ml",
      "description": null,
      "price": 55500,
      "price_text": "55500 DZD",
      "currency": "DZD",
      "image_url": null,
      "brand": "NISHANE",
      "sku": "3538",
      "is_active": true,
      "stock_quantity": 0,
      "url": "https://pafen-dz.com/product/3538-nishane-hacivat-x-extrait-de-parfum-100-ml"
    },
    {
      "name": "XERJOFF MORE THAN WORDS EDP 100 ML",
      "slug": "xerjoff-more-than-words-edp-100-ml",
      "description": null,
      "price": 55500,
      "price_text": "55500 DZD",
      "currency": "DZD",
      "image_url": null,
      "brand": "XERJOFF",
      "sku": "2157",
      "is_active": true,
      "stock_quantity": 0,
      "url": "https://pafen-dz.com/product/2157-xerjoff-more-than-words-edp-100-ml"
    },
    {
      "name": "XERJOFF MUSE EDP 100 ML",
      "slug": "xerjoff-muse-edp-100-ml",
      "description": null,
      "price": 54500,
      "price_text": "54500 DZD",
      "currency": "DZD",
      "image_url": null,
      "brand": "XERJOFF",
      "sku": "2158",
      "is_active": true,
      "stock_quantity": 0,
      "url": "https://pafen-dz.com/product/2158-xerjoff-muse-edp-100-ml"
    },
    {
      "name": "AMOUAGE INTERLUDE BLACK IRIS MAN EDP 100 ML",
      "slug": "amouage-interlude-black-iris-man-edp-100-ml",
      "description": null,
      "price": 52000,
      "price_text": "52000 DZD",
      "currency": "DZD",
      "image_url": null,
      "brand": "AMOUAGE",
      "sku": "3830",
      "is_active": true,
      "stock_quantity": 0,
      "url": "https://pafen-dz.com/product/3830-amouage-interlude-black-iris-man-edp-100-ml"
    },
    {
      "name": "NISHANE HACIVAT EXTRAIT DE PARFUM100 ML",
      "slug": "nishane-hacivat-extrait-de-parfum100-ml",
      "description": null,
      "price": 51500,
      "price_text": "51500 DZD",
      "currency": "DZD",
      "image_url": null,
      "brand": "NISHANE",
      "sku": "4018",
      "is_active": true,
      "stock_quantity": 0,
      "url": "https://pafen-dz.com/product/4018-nishane-hacivat-extrait-de-parfum100-ml"
    },
    {
      "name": "XERJOFF DECAS EDP 100 ML",
      "slug": "xerjoff-decas-edp-100-ml",
      "description": null,
      "price": 51000,
      "price_text": "51000 DZD",
      "currency": "DZD",
      "image_url": null,
      "brand": "XERJOFF",
      "sku": "2154",
      "is_active": true,
      "stock_quantity": 0,
      "url": "https://pafen-dz.com/product/2154-xerjoff-decas-edp-100-ml"
    },
    {
      "name": "MORESQUE PARFUM ROSA EKATERINA EDP 50 ML",
      "slug": "moresque-parfum-rosa-ekaterina-edp-50-ml",
      "description": null,
      "price": 50000,
      "price_text": "50000 DZD",
      "currency": "DZD",
      "image_url": null,
      "brand": "MORESQUE",
      "sku": "3473",
      "is_active": true,
      "stock_quantity": 0,
      "url": "https://pafen-dz.com/product/3473-moresque-parfum-rosa-ekaterina-edp-50-ml"
    },
    {
      "name": "NISHANE ANI EXTRAIT DE PARFUM 100 ML",
      "slug": "nishane-ani-extrait-de-parfum-100-ml",
      "description": null,
      "price": 47000,
      "price_text": "47000 DZD",
      "currency": "DZD",
      "image_url": null,
      "brand": "NISHANE",
      "sku": "1782",
      "is_active": true,
      "stock_quantity": 0,
      "url": "https://pafen-dz.com/product/1782-ani-extrait-de-parfum"
    },
    {
      "name": "NISHANE WULONG CHA EXTRAIT DE PARFUM 100 ML",
      "slug": "nishane-wulong-cha-extrait-de-parfum-100-ml",
      "description": null,
      "price": 46500,
      "price_text": "46500 DZD",
      "currency": "DZD",
      "image_url": null,
      "brand": "NISHANE",
      "sku": "3700",
      "is_active": true,
      "stock_quantity": 0,
      "url": "https://pafen-dz.com/product/3700-nishane-wulong-cha-extrait-de-parfum-100-ml"
    },
    {
      "name": "PARFUMS DE MARLY PARIS PEGASUS EDP 125 ML",
      "slug": "parfums-de-marly-paris-pegasus-edp-125-ml",
      "description": null,
      "price": 45000,
      "price_text": "45000 DZD",
      "currency": "DZD",
      "image_url": null,
      "brand": "PARFUMS",
      "sku": "3695",
      "is_active": true,
      "stock_quantity": 0,
      "url": "https://pafen-dz.com/product/3695-parfums-de-marly-paris-pegasus-edp-125-ml"
    },
    {
      "name": "DIOR SAUVAGE ELIXIR EDP 100 ml",
      "slug": "dior-sauvage-elixir-edp-100-ml",
      "description": null,
      "price": 43500,
      "price_text": "43500 DZD",
      "currency": "DZD",
      "image_url": null,
      "brand": "DIOR",
      "sku": "2990",
      "is_active": true,
      "stock_quantity": 0,
      "url": "https://pafen-dz.com/product/2990-sauvage-lixir-edp-100-ml"
    },
    {
      "name": "BLEND OUD VOYAGE MEMORIES SANTAL PONDICHERRY EDP 75 ML",
      "slug": "blend-oud-voyage-memories-santal-pondicherry-edp-75-ml",
      "description": null,
      "price": 35000,
      "price_text": "35000 DZD",
      "currency": "DZD",
      "image_url": null,
      "brand": "BLEND",
      "sku": "3488",
      "is_active": true,
      "stock_quantity": 0,
      "url": "https://pafen-dz.com/product/3488-blend-oud-voyage-memories-santal-pondicherry-edp-75-ml"
    },
    {
      "name": "TOM FORD EXTREME NOIR EDP 100ML",
      "slug": "tom-ford-extreme-noir-edp-100ml",
      "description": null,
      "price": 34000,
      "price_text": "34000 DZD",
      "currency": "DZD",
      "image_url": null,
      "brand": "TOM FORD",
      "sku": "484",
      "is_active": true,
      "stock_quantity": 0,
      "url": "https://pafen-dz.com/product/484-tom-ford-extreme-noir-100ml-edp"
    },
    {
      "name": "ARMANI ACQUA DI GIO PARFUM 200 ML",
      "slug": "armani-acqua-di-gio-parfum-200-ml",
      "description": null,
      "price": 33000,
      "price_text": "33000 DZD",
      "currency": "DZD",
      "image_url": null,
      "brand": "ARMANI",
      "sku": "3833",
      "is_active": true,
      "stock_quantity": 0,
      "url": "https://pafen-dz.com/product/3833-armani-acqua-di-gio-parfum-200-ml"
    },
    {
      "name": "TOM FORD OMBRE LEATHER EDP 100 ML",
      "slug": "tom-ford-ombre-leather-edp-100-ml",
      "description": null,
      "price": 32000,
      "price_text": "32000 DZD",
      "currency": "DZD",
      "image_url": null,
      "brand": "TOM FORD",
      "sku": "3121",
      "is_active": true,
      "stock_quantity": 0,
      "url": "https://pafen-dz.com/product/3121-tom-ford-ombre-leather-edp-100-ml"
    },
    {
      "name": "JPG SCANDAL HOMME EDP INTENSE 100 ML",
      "slug": "jpg-scandal-homme-edp-intense-100-ml",
      "description": null,
      "price": 30000,
      "price_text": "30000 DZD",
      "currency": "DZD",
      "image_url": null,
      "brand": "JPG",
      "sku": "4008",
      "is_active": true,
      "stock_quantity": 0,
      "url": "https://pafen-dz.com/product/4008-jpg-scandal-homme-edp-intense-100-ml"
    },
    {
      "name": "NANSHE EXTRAIT DE PARFUM 50 ML.",
      "slug": "nanshe-extrait-de-parfum-50-ml",
      "description": null,
      "price": 30000,
      "price_text": "30000 DZD",
      "currency": "DZD",
      "image_url": null,
      "brand": "NANSHE",
      "sku": "1783",
      "is_active": true,
      "stock_quantity": 0,
      "url": "https://pafen-dz.com/product/1783-nanshe-extrait-de-parfum-50-ml"
    },
    {
      "name": "TOM FORD BLACK ORCHID EDP 100ML",
      "slug": "tom-ford-black-orchid-edp-100ml",
      "description": null,
      "price": 30000,
      "price_text": "30000 DZD",
      "currency": "DZD",
      "image_url": null,
      "brand": "TOM FORD",
      "sku": "475",
      "is_active": true,
      "stock_quantity": 0,
      "url": "https://pafen-dz.com/product/475-tom-ford-black-orchid-100ml-edp"
    },
    {
      "name": "YSL MY SLF LE PARFUM 100 ML",
      "slug": "ysl-my-slf-le-parfum-100-ml",
      "description": null,
      "price": 29000,
      "price_text": "29000 DZD",
      "currency": "DZD",
      "image_url": null,
      "brand": "YSL",
      "sku": "3805",
      "is_active": true,
      "stock_quantity": 0,
      "url": "https://pafen-dz.com/product/3805-ysl-my-slf-le-parfum-100-ml"
    },
    {
      "name": "YSL Y LE PARFUM 100 ML 2025",
      "slug": "ysl-y-le-parfum-100-ml-2025",
      "description": null,
      "price": 28500,
      "price_text": "28500 DZD",
      "currency": "DZD",
      "image_url": null,
      "brand": "YSL",
      "sku": "4011",
      "is_active": true,
      "stock_quantity": 0,
      "url": "https://pafen-dz.com/product/4011-ysl-y-le-parfum-100-ml-2025"
    },
    {
      "name": "JPG LE MALE ELIXIR PARFUM 125 ML",
      "slug": "jpg-le-male-elixir-parfum-125-ml",
      "description": null,
      "price": 28500,
      "price_text": "28500 DZD",
      "currency": "DZD",
      "image_url": null,
      "brand": "JPG",
      "sku": "3205",
      "is_active": true,
      "stock_quantity": 0,
      "url": "https://pafen-dz.com/product/3205-jpg-le-male-elixir-parfum-125-ml"
    },
    {
      "name": "JPG LE BEAU PARADISE GARDEN EDP 125 ML",
      "slug": "jpg-le-beau-paradise-garden-edp-125-ml",
      "description": null,
      "price": 28000,
      "price_text": "28000 DZD",
      "currency": "DZD",
      "image_url": null,
      "brand": "JPG",
      "sku": "3665",
      "is_active": true,
      "stock_quantity": 0,
      "url": "https://pafen-dz.com/product/3665-jpg-le-beau-paradise-garden-edp-125-ml"
    },
    {
      "name": "GUCCI OUD INTENSE EDP 90 ML",
      "slug": "gucci-oud-intense-edp-90-ml",
      "description": null,
      "price": 28000,
      "price_text": "28000 DZD",
      "currency": "DZD",
      "image_url": null,
      "brand": "GUCCI",
      "sku": "461",
      "is_active": true,
      "stock_quantity": 0,
      "url": "https://pafen-dz.com/product/461-gucci-oud-intense-90-ml-edp"
    },
    {
      "name": "ARMANI ACQUA DI GIO EDP 200 ML",
      "slug": "armani-acqua-di-gio-edp-200-ml",
      "description": null,
      "price": 27000,
      "price_text": "27000 DZD",
      "currency": "DZD",
      "image_url": null,
      "brand": "ARMANI",
      "sku": "3945",
      "is_active": true,
      "stock_quantity": 0,
      "url": "https://pafen-dz.com/product/3945-armani-acqua-di-gio-edp-200-ml"
    },
    {
      "name": "JPG SCANDAL ABSOLU PARFUM HOMME 100 ML",
      "slug": "jpg-scandal-absolu-parfum-homme-100-ml",
      "description": null,
      "price": 27000,
      "price_text": "27000 DZD",
      "currency": "DZD",
      "image_url": null,
      "brand": "JPG",
      "sku": "3680",
      "is_active": true,
      "stock_quantity": 0,
      "url": "https://pafen-dz.com/product/3680-jpg-scandal-absolu-parfum-homme-100-ml"
    },
    {
      "name": "JPG SCANDAL LE PARFUM 100 ML HOMME",
      "slug": "jpg-scandal-le-parfum-100-ml-homme",
      "description": null,
      "price": 27000,
      "price_text": "27000 DZD",
      "currency": "DZD",
      "image_url": null,
      "brand": "JPG",
      "sku": "2463",
      "is_active": true,
      "stock_quantity": 0,
      "url": "https://pafen-dz.com/product/2463-scandal-le-parfum-pour-homme-le-parfum-eau-de-parfu"
    },
    {
      "name": "JPG LE MALE EDP INTENSE 125 ML",
      "slug": "jpg-le-male-edp-intense-125-ml",
      "description": null,
      "price": 27000,
      "price_text": "27000 DZD",
      "currency": "DZD",
      "image_url": null,
      "brand": "JPG",
      "sku": "957",
      "is_active": true,
      "stock_quantity": 0,
      "url": "https://pafen-dz.com/product/957-jpg-le-male-edp-intense-125ml"
    },
    {
      "name": "ARMANI ACQUA DI GIO ELIXIR 50 ML",
      "slug": "armani-acqua-di-gio-elixir-50-ml",
      "description": null,
      "price": 26000,
      "price_text": "26000 DZD",
      "currency": "DZD",
      "image_url": null,
      "brand": "ARMANI",
      "sku": "4037",
      "is_active": true,
      "stock_quantity": 0,
      "url": "https://pafen-dz.com/product/4037-armani-acqua-di-gio-elixir-50-ml"
    },
    {
      "name": "ARMANI STRONGER WITH YOU PARFUM 100 ML",
      "slug": "armani-stronger-with-you-parfum-100-ml",
      "description": null,
      "price": 26000,
      "price_text": "26000 DZD",
      "currency": "DZD",
      "image_url": null,
      "brand": "ARMANI",
      "sku": "3990",
      "is_active": true,
      "stock_quantity": 0,
      "url": "https://pafen-dz.com/product/3990-armani-stronger-with-you-parfum-100-ml"
    },
    {
      "name": "LOUIS VUITTON HEURES D'ABSENCE EDP 200 ML",
      "slug": "louis-vuitton-heures-d-absence-edp-200-ml",
      "description": null,
      "price": 120000,
      "price_text": "120000 DZD",
      "currency": "DZD",
      "image_url": null,
      "brand": "LOUIS",
      "sku": "3455",
      "is_active": true,
      "stock_quantity": 0,
      "url": "https://pafen-dz.com/product/3455-louis-vuitton-heures-dabsence-edp-200-ml"
    },
    {
      "name": "MFK BACCARAT ROUGE 540 EDP 200 ML",
      "slug": "mfk-baccarat-rouge-540-edp-200-ml",
      "description": null,
      "price": 90000,
      "price_text": "90000 DZD",
      "currency": "DZD",
      "image_url": null,
      "brand": "MFK",
      "sku": "3442",
      "is_active": true,
      "stock_quantity": 0,
      "url": "https://pafen-dz.com/product/3442-mfk-baccarat-rouge-540-edp-200-ml"
    },
    {
      "name": "PARFUMS DE MARLY DELINA EDP 75 ML",
      "slug": "parfums-de-marly-delina-edp-75-ml",
      "description": null,
      "price": 53000,
      "price_text": "53000 DZD",
      "currency": "DZD",
      "image_url": null,
      "brand": "PARFUMS",
      "sku": "3587",
      "is_active": true,
      "stock_quantity": 0,
      "url": "https://pafen-dz.com/product/3587-parfums-de-marly-delina-edp-75-ml"
    },
    {
      "name": "PARFUM DE MARLY PARIS DELINA LA ROSEE EDP 75 ML",
      "slug": "parfum-de-marly-paris-delina-la-rosee-edp-75-ml",
      "description": null,
      "price": 51000,
      "price_text": "51000 DZD",
      "currency": "DZD",
      "image_url": null,
      "brand": "PARFUM",
      "sku": "2994",
      "is_active": true,
      "stock_quantity": 0,
      "url": "https://pafen-dz.com/product/2994-parfum-de-marly-paris-delina-la-rosee-edp-75-ml"
    },
    {
      "name": "ROJA RISQUE ESSENCE POUR FEMME EDP 100ML",
      "slug": "roja-risque-essence-pour-femme-edp-100ml",
      "description": null,
      "price": 51000,
      "price_text": "51000 DZD",
      "currency": "DZD",
      "image_url": null,
      "brand": "ROJA",
      "sku": "2543",
      "is_active": true,
      "stock_quantity": 0,
      "url": "https://pafen-dz.com/product/2543-roja-risque-essence-pour-femme-edp-100ml"
    },
    {
      "name": "PRADA PARADOXE EDP INTENSE 90 ML",
      "slug": "prada-paradoxe-edp-intense-90-ml",
      "description": null,
      "price": 31500,
      "price_text": "31500 DZD",
      "currency": "DZD",
      "image_url": null,
      "brand": "PRADA",
      "sku": "3333",
      "is_active": true,
      "stock_quantity": 0,
      "url": "https://pafen-dz.com/product/3333-prada-paradoxe-edp-intense-90-ml"
    },
    {
      "name": "YSL LIBRE L'ABSOLU PLATINE 90 ML",
      "slug": "ysl-libre-l-absolu-platine-90-ml",
      "description": null,
      "price": 31000,
      "price_text": "31000 DZD",
      "currency": "DZD",
      "image_url": null,
      "brand": "YSL",
      "sku": "3312",
      "is_active": true,
      "stock_quantity": 0,
      "url": "https://pafen-dz.com/product/3312-ysl-libre-labsolu-platine-90-ml"
    },
    {
      "name": "YSL LIBRE L'EAU NUE PARFUM DE PEAU 90 ML",
      "slug": "ysl-libre-l-eau-nue-parfum-de-peau-90-ml",
      "description": null,
      "price": 30000,
      "price_text": "30000 DZD",
      "currency": "DZD",
      "image_url": null,
      "brand": "YSL",
      "sku": "4039",
      "is_active": true,
      "stock_quantity": 0,
      "url": "https://pafen-dz.com/product/4039-ysl-libre-leau-nue-parfum-de-peau-90-ml"
    },
    {
      "name": "JPG DIVINE LE PARFUM 100 ML",
      "slug": "jpg-divine-le-parfum-100-ml",
      "description": null,
      "price": 30000,
      "price_text": "30000 DZD",
      "currency": "DZD",
      "image_url": null,
      "brand": "JPG",
      "sku": "3823",
      "is_active": true,
      "stock_quantity": 0,
      "url": "https://pafen-dz.com/product/3823-jpg-divine-le-parfum-100-ml"
    }
  ]
}
